news-wrapper-api/__init__.py
news-wrapper-api/api.py
news-wrapper-api/utils/__init__.py
news-wrapper-api/utils/abp_news.py
news-wrapper-api/utils/bbc.py
news-wrapper-api/utils/india_today.py
wrapper_news_api/__init__.py
wrapper_news_api/api.py
wrapper_news_api-0.6.dist-info/METADATA
wrapper_news_api-0.6.dist-info/WHEEL
wrapper_news_api-0.6.dist-info/top_level.txt
wrapper_news_api-0.6.dist-info/RECORD
