Metadata-Version: 2.1
Name: wrapper_news_api
Version: 0.6
Summary: A Python package to fetch news from BBC, ABP News, and India Today
Home-page: https://github.com/shreyasissleepy/NewsAPI
Author: Shreyas Naik
Author-email: shreyasnaik179@gmail.com
License: MIT
Classifier: Development Status :: 3 - Alpha
Classifier: Intended Audience :: Developers
Classifier: License :: OSI Approved :: MIT License
Classifier: Programming Language :: Python :: 3
Classifier: Programming Language :: Python :: 3.7
Classifier: Programming Language :: Python :: 3.8
Classifier: Programming Language :: Python :: 3.9
Requires-Python: >=3.7
Requires-Dist: requests
Requires-Dist: beautifulsoup4
